saleyo-1.3.4.dist-info/METADATA
saleyo-1.3.4.dist-info/WHEEL
saleyo-1.3.4.dist-info/entry_points.txt
saleyo-1.3.4.dist-info/licenses/LICENSE
saleyo/__init__.py
saleyo/base/__init__.py
saleyo/base/broadcast.py
saleyo/base/template.py
saleyo/base/toolchain.py
saleyo/base/typing.py
saleyo/broadcast/__init__.py
saleyo/broadcast/compile/__init__.py
saleyo/broadcast/compile/activate.py
saleyo/broadcast/file/__init__.py
saleyo/broadcast/file/activate.py
saleyo/broadcast/importmod/__init__.py
saleyo/broadcast/importmod/activate.py
saleyo/decorator/__init__.py
saleyo/decorator/ancestor.py
saleyo/decorator/compile.py
saleyo/decorator/file.py
saleyo/decorator/mixin.py
saleyo/operation/__init__.py
saleyo/operation/accessor.py
saleyo/operation/hook.py
saleyo/operation/intercept.py
saleyo/operation/modify.py
saleyo/operation/overwrite.py
saleyo/operation/processor.py
saleyo/parser/__init__.py
saleyo/parser/token.py
saleyo-1.3.4.dist-info/RECORD
