Metadata-Version: 2.1
Name: saleyo
Version: 1.3.4
Summary: Saleyo is a lightwight scalable Python AOP framework, easy to use and integrate.
Author-Email: H2Sxxa <h2sxxa0w0@gmail.com>
License: MIT
Project-URL: Homepage, https://pypi.org/project/saleyo/
Project-URL: Repository, https://github.com/H2Sxxa/saleyo
Project-URL: Issues, https://github.com/H2Sxxa/saleyo/issues
Requires-Python: >=3.8
